mdtable2csv/__init__.py
mdtable2csv/cli.py
mdtable2csv-0.1.0.dist-info/METADATA
mdtable2csv-0.1.0.dist-info/WHEEL
mdtable2csv-0.1.0.dist-info/entry_points.txt
mdtable2csv-0.1.0.dist-info/licenses/LICENSE
mdtable2csv-0.1.0.dist-info/RECORD
