Metadata-Version: 2.4
Name: mdtable2csv
Version: 0.1.0
Summary: Convert Markdown tables to CSV
Project-URL: Homepage, https://github.com/samueltinnerholm/mdtable2csv
Project-URL: Repository, https://github.com/samueltinnerholm/mdtable2csv
Project-URL: Issues, https://github.com/samueltinnerholm/mdtable2csv/issues
Author-email: "Samuel EF. Tinnerholm" <samuel.tinnerholm@gmail.com>
License: MIT License
License-File: LICENSE
Classifier: License :: OSI Approved :: MIT License
Classifier: Operating System :: OS Independent
Classifier: Programming Language :: Python :: 3
Classifier: Programming Language :: Python :: 3 :: Only
Requires-Python: >=3.8
Requires-Dist: beautifulsoup4
Requires-Dist: flask
Requires-Dist: requests
